causalpy/__init__.py
causalpy/custom_exceptions.py
causalpy/plot_utils.py
causalpy/pymc_models.py
causalpy/reporting.py
causalpy/skl_models.py
causalpy/utils.py
causalpy/version.py
causalpy/data/AJR2001.csv
causalpy/data/GDP_in_dollars_billions.csv
causalpy/data/PISA18sampleScale.csv
causalpy/data/__init__.py
causalpy/data/ancova_generated.csv
causalpy/data/banks.csv
causalpy/data/datasets.py
causalpy/data/deaths_and_temps_england_wales.csv
causalpy/data/did.csv
causalpy/data/drinking.csv
causalpy/data/geolift1.csv
causalpy/data/geolift_multi_cell.csv
causalpy/data/gt_social_media_data.csv
causalpy/data/its.csv
causalpy/data/its_simple.csv
causalpy/data/lalonde.csv
causalpy/data/nets_df.csv
causalpy/data/nhefs.csv
causalpy/data/regression_discontinuity.csv
causalpy/data/schoolingReturns.csv
causalpy/data/simulate_data.py
causalpy/data/synthetic_control.csv
causalpy/experiments/__init__.py
causalpy/experiments/base.py
causalpy/experiments/diff_in_diff.py
causalpy/experiments/instrumental_variable.py
causalpy/experiments/interrupted_time_series.py
causalpy/experiments/inverse_propensity_weighting.py
causalpy/experiments/prepostnegd.py
causalpy/experiments/regression_discontinuity.py
causalpy/experiments/regression_kink.py
causalpy/experiments/synthetic_control.py
causalpy-0.6.0.dist-info/licenses/LICENSE
causalpy-0.6.0.dist-info/METADATA
causalpy-0.6.0.dist-info/WHEEL
causalpy-0.6.0.dist-info/top_level.txt
causalpy-0.6.0.dist-info/RECORD
