Metadata-Version: 2.4
Name: CausalPy
Version: 0.6.0
Summary: Causal inference for quasi-experiments in Python
Author-email: Ben Vincent <ben.vincent@pymc-labs.com>
License:                                  Apache License
Project-URL: Homepage, https://github.com/pymc-labs/CausalPy
Project-URL: Bug Reports, https://github.com/pymc-labs/CausalPy/issues
Project-URL: Source, https://github.com/pymc-labs/CausalPy
Requires-Python: >=3.11
License-File: LICENSE
Requires-Dist: arviz>=0.14.0
Requires-Dist: graphviz
Requires-Dist: ipython!=8.7.0
Requires-Dist: matplotlib>=3.5.3
Requires-Dist: numpy
Requires-Dist: pandas
Requires-Dist: patsy
Requires-Dist: pymc>=5.15.1
Requires-Dist: scikit-learn>=1
Requires-Dist: scipy
Requires-Dist: seaborn>=0.11.2
Requires-Dist: statsmodels
Requires-Dist: xarray>=v2022.11.0
Requires-Dist: pymc-extras>=0.3.0
Provides-Extra: dev
Requires-Dist: pathlib; extra == "dev"
Requires-Dist: pre-commit; extra == "dev"
Requires-Dist: twine; extra == "dev"
Requires-Dist: interrogate; extra == "dev"
Requires-Dist: codespell; extra == "dev"
Requires-Dist: nbformat; extra == "dev"
Requires-Dist: nbconvert; extra == "dev"
Provides-Extra: docs
Requires-Dist: ipykernel; extra == "docs"
Requires-Dist: daft-pgm; extra == "docs"
Requires-Dist: linkify-it-py; extra == "docs"
Requires-Dist: myst-nb<=1.0.0; extra == "docs"
Requires-Dist: pathlib; extra == "docs"
Requires-Dist: pylint; extra == "docs"
Requires-Dist: sphinx; extra == "docs"
Requires-Dist: sphinx-autodoc-typehints; extra == "docs"
Requires-Dist: sphinx_autodoc_defaultargs; extra == "docs"
Requires-Dist: labs-sphinx-theme; extra == "docs"
Requires-Dist: sphinx-copybutton; extra == "docs"
Requires-Dist: sphinx-rtd-theme; extra == "docs"
Requires-Dist: statsmodels; extra == "docs"
Requires-Dist: sphinxcontrib-bibtex; extra == "docs"
Requires-Dist: sphinx-notfound-page; extra == "docs"
Requires-Dist: ipywidgets; extra == "docs"
Requires-Dist: sphinx-design; extra == "docs"
Requires-Dist: sphinx-togglebutton; extra == "docs"
Provides-Extra: lint
Requires-Dist: interrogate; extra == "lint"
Requires-Dist: pre-commit; extra == "lint"
Requires-Dist: ruff; extra == "lint"
Requires-Dist: mypy; extra == "lint"
Provides-Extra: test
Requires-Dist: pytest; extra == "test"
Requires-Dist: pytest-cov; extra == "test"
Requires-Dist: codespell; extra == "test"
Requires-Dist: nbformat; extra == "test"
Requires-Dist: nbconvert; extra == "test"
Dynamic: license-file
